microstrategy_api/__init__.py
microstrategy_api/command_manager.py
microstrategy_api/microstrategy_com.py
microstrategy_api/microstrategy_selenium/__init__.py
microstrategy_api/microstrategy_selenium/dashboard_functions.py
microstrategy_api/microstrategy_selenium/landing_page_functions.py
microstrategy_api/mstr_rest_api_facade/__init__.py
microstrategy_api/mstr_rest_api_facade/api_error.py
microstrategy_api/selenium_driver/__init__.py
microstrategy_api/selenium_driver/driver.py
microstrategy_api/selenium_driver/find_elements.py
microstrategy_api/selenium_driver/wait_multi.py
microstrategy_api/task_proc/__init__.py
microstrategy_api/task_proc/_get_constants.py
microstrategy_api/task_proc/attribute.py
microstrategy_api/task_proc/attribute_form.py
microstrategy_api/task_proc/bit_set.py
microstrategy_api/task_proc/doc_execution_flags.py
microstrategy_api/task_proc/document.py
microstrategy_api/task_proc/exceptions.py
microstrategy_api/task_proc/executable_base.py
microstrategy_api/task_proc/memoize_class.py
microstrategy_api/task_proc/message.py
microstrategy_api/task_proc/metadata_object.py
microstrategy_api/task_proc/metric.py
microstrategy_api/task_proc/object_type.py
microstrategy_api/task_proc/privilege_types.py
microstrategy_api/task_proc/prompt.py
microstrategy_api/task_proc/report.py
microstrategy_api/task_proc/report_execution_flags.py
microstrategy_api/task_proc/status.py
microstrategy_api/task_proc/task_proc.py
microstrategy_api/timer.py
microstrategy_api-0.6.5.dist-info/license.txt
microstrategy_api-0.6.5.dist-info/WHEEL
microstrategy_api-0.6.5.dist-info/METADATA
microstrategy_api-0.6.5.dist-info/RECORD
