Metadata-Version: 2.1
Name: microstrategy-api
Version: 0.6.5
Summary: Python API library for interacting with MicroStrategy Intelligence Server and/or MicroStrategy Web Server.
Home-page: https://github.com/arcann/mstr_python_api
License: MIT
Author: Derek Wood
Requires-Python: >=3.6,<4.0
Classifier: License :: OSI Approved :: MIT License
Classifier: Programming Language :: Python :: 3
Classifier: Programming Language :: Python :: 3.6
Classifier: Programming Language :: Python :: 3.7
Classifier: Programming Language :: Python :: 3.8
Classifier: Programming Language :: Python :: 3.9
Requires-Dist: beautifulsoup4 (>=4.10.0,<5.0.0)
Requires-Dist: keyring (>=23.2.1,<24.0.0)
Requires-Dist: pywin32 (>=302,<303)
Requires-Dist: requests (>=2.24.0,<3.0.0)
Project-URL: Repository, https://github.com/arcann/mstr_python_api
